{
  "sections": {
    "hero": {
      "type": "hero",
      "settings": {
        "eyebrow": "Nigeria's Hair Supplier",
        "title": "Quality You Can Trust.",
        "title_italic": "From Supplier to Door.",
        "lead": "<strong>Global Hair Direct</strong> supplies braiding hair, bulk hair, and premium hair extensions directly to salon owners, distributors, and individual buyers across all 36 Nigerian states — with consistent quality, transparent pricing, and accountable delivery every order.",
        "tagline": "Transparent pricing. Accountable delivery.",
        "cta1_text": "Place Pre-Order",
        "cta1_url": "/collections/all",
        "cta2_text": "View Catalogue",
        "cta2_url": "/collections/all",
        "cta3_text": "Wholesale Inquiry",
        "cta3_url": "/pages/contact",
        "panel_title": "Current Stock",
        "notice_tag": "Pre-Order Offer — Active Now",
        "notice_text": "<strong>Bone Straight, French Curl &amp; Deep Wave</strong> — order now and receive 5% discount on your total. Wholesale pricing available for salon and distributor accounts.",
        "notice_cta_text": "Place Pre-Order",
        "notice_cta_url": "/collections/all"
      },
      "blocks": {
        "hero_stat_1": {
          "type": "stat",
          "settings": { "value": "700", "label": "Units in stock" }
        },
        "hero_stat_2": {
          "type": "stat",
          "settings": { "value": "3", "label": "Hair types" }
        },
        "hero_stat_3": {
          "type": "stat",
          "settings": { "value": "36", "label": "States covered" }
        },
        "hero_stat_4": {
          "type": "stat",
          "settings": { "value": "4+", "label": "Colour options" }
        }
      },
      "block_order": [
        "hero_stat_1",
        "hero_stat_2",
        "hero_stat_3",
        "hero_stat_4"
      ]
    },
    "featured_products": {
      "type": "featured-products",
      "settings": {
        "eyebrow": "Product Catalogue",
        "title": "Current Stock &",
        "title_italic": "Pre-Order Lines",
        "products_limit": 4,
        "show_view_all": false,
        "view_all_text": "View Full Catalogue",
        "view_all_url": "/collections/all"
      },
      "blocks": {
        "fp_f1": { "type": "filter", "settings": { "label": "Braiding Hair", "filter_key": "braiding-hair" } },
        "fp_f2": { "type": "filter", "settings": { "label": "Curl Hair", "filter_key": "curl-hair" } },
        "fp_f3": { "type": "filter", "settings": { "label": "Deep Wave", "filter_key": "deep-wave" } },
        "fp_f4": { "type": "filter", "settings": { "label": "Coming Soon", "filter_key": "coming-soon" } },
        "fp_c1": {
          "type": "product_card",
          "settings": {
            "title": "Bone Straight 30inch",
            "category": "Braiding Hair",
            "vendor": "150g · Colours: 1B, 27#, BUG, 613#",
            "price": "$1.00",
            "price_label": "Per unit · MOQ 60",
            "badge_type": "instock",
            "badge": "In Stock",
            "filter_key": "braiding-hair"
          }
        },
        "fp_c2": {
          "type": "product_card",
          "settings": {
            "title": "French Curl 22inch",
            "category": "Curl Hair",
            "vendor": "150g · Colours: 1B, 27#, BUG, 613#",
            "price": "$1.00",
            "price_label": "Per unit · MOQ 25",
            "badge_type": "instock",
            "badge": "In Stock",
            "filter_key": "curl-hair"
          }
        },
        "fp_c3": {
          "type": "product_card",
          "settings": {
            "title": "Deep Wave Bulk 22inch",
            "category": "Bulk Hair",
            "vendor": "100g · Colours: 1B, 27#, BUG, 613#",
            "price": "$2.00",
            "price_label": "Per unit · MOQ 15",
            "badge_type": "instock",
            "badge": "In Stock",
            "filter_key": "deep-wave"
          }
        },
        "fp_c4": {
          "type": "product_card",
          "settings": {
            "title": "Premium Bundles & Frontals",
            "category": "Human Hair",
            "vendor": "Raw Virgin · Launching soon",
            "price": "Notify Me",
            "price_label": "Pre-register now",
            "badge_type": "soon",
            "badge": "Coming Soon",
            "filter_key": "coming-soon"
          }
        }
      },
      "block_order": ["fp_f1", "fp_f2", "fp_f3", "fp_f4", "fp_c1", "fp_c2", "fp_c3", "fp_c4"]
    },
    "divider_2": { "type": "section-divider", "settings": {} },
    "about_us": {
      "type": "about-us",
      "settings": {
        "left_eyebrow": "About Us",
        "title": "One Standard.",
        "title_italic": "Consistently Applied.",
        "lead": "Global Hair Direct supplies quality hair products directly to Nigerian buyers — salon owners, beauty distributors, and individuals — with fair wholesale pricing, multiple colour options, and reliable nationwide delivery on every order.",
        "right_eyebrow": "By the Numbers",
        "cta_text": "Request Wholesale Account",
        "cta_url": "/pages/contact"
      },
      "blocks": {
        "about_check_1": {
          "type": "check_item",
          "settings": {
            "is_negative": false,
            "label": "What we are:",
            "text": "A direct hair supplier servicing salon owners, distributors, and individual buyers across all 36 Nigerian states."
          }
        },
        "about_check_2": {
          "type": "check_item",
          "settings": {
            "is_negative": false,
            "label": "What we supply:",
            "text": "Braiding hair, bulk hair, and curl hair — with premium human hair extensions launching soon."
          }
        },
        "about_check_3": {
          "type": "check_item",
          "settings": {
            "is_negative": false,
            "label": "What we offer:",
            "text": "Wholesale pricing tiers, pre-order discounts, and dedicated support for salon and distributor accounts."
          }
        },
        "about_check_4": {
          "type": "check_item",
          "settings": {
            "is_negative": true,
            "label": "What we do not do:",
            "text": "Process unconfirmed orders, substitute colours without approval, or ship outside Nigeria."
          }
        },
        "about_stat_1": {
          "type": "stat",
          "settings": { "value": "700+", "label": "Units available in current stock" }
        },
        "about_stat_2": {
          "type": "stat",
          "settings": { "value": "3", "label": "Hair types stocked — more coming" }
        },
        "about_stat_3": {
          "type": "stat",
          "settings": { "value": "4+", "label": "Colour options per product line" }
        },
        "about_stat_4": {
          "type": "stat",
          "settings": { "value": "36", "label": "States covered nationwide" }
        }
      },
      "block_order": [
        "about_check_1",
        "about_check_2",
        "about_check_3",
        "about_check_4",
        "about_stat_1",
        "about_stat_2",
        "about_stat_3",
        "about_stat_4"
      ]
    },
    "buyer_tiers": {
      "type": "buyer-tiers",
      "settings": {
        "eyebrow": "Buyer Tiers",
        "title": "Structured Pricing.",
        "title_italic": "Three Account Tiers.",
        "lead": "Pricing reflects order volume and account type. All pricing confirmed in writing before any order is processed. No hidden charges."
      },
      "blocks": {
        "tier_1": {
          "type": "tier",
          "settings": {
            "tier_number": "Tier 01",
            "name": "Individual Buyer",
            "range": "Small quantities · No minimums",
            "perks": "Order any colour combination per product\nFree delivery on orders above ₦50,000\n30-day satisfaction guarantee\nWhatsApp tracking from dispatch to door",
            "discount": "Retail",
            "discount_label": "Standard pricing",
            "cta_text": "Shop Now",
            "cta_url": "/collections/all",
            "featured": false
          }
        },
        "tier_2": {
          "type": "tier",
          "settings": {
            "tier_number": "Tier 02",
            "name": "Salon Owner",
            "range": "Medium volume · Regular orders",
            "perks": "Salon-tier pricing across all hair types\nMixed colour orders accepted per product\nMonthly standing order option available\nPriority dispatch and dedicated support\nFirst access to new product launches",
            "discount": "–15%",
            "discount_label": "Off retail pricing",
            "cta_text": "Apply Now",
            "cta_url": "/pages/contact",
            "featured": true
          }
        },
        "tier_3": {
          "type": "tier",
          "settings": {
            "tier_number": "Tier 03",
            "name": "Wholesale Distributor",
            "range": "High volume · Bulk orders",
            "perks": "Lowest per-unit pricing available\nFull colour and product mix per order\nCustom packaging options available\nDedicated account manager assigned\nNet-30 payment terms for verified accounts\nMulti-state distribution support",
            "discount": "–35%",
            "discount_label": "Off retail pricing",
            "cta_text": "Apply Now",
            "cta_url": "/pages/contact",
            "featured": false
          }
        }
      },
      "block_order": ["tier_1", "tier_2", "tier_3"]
    },
    "how_to_order": {
      "type": "how-to-order",
      "settings": {
        "eyebrow": "How to Order",
        "title": "Simple Process.",
        "title_italic": "Four Steps to Delivery.",
        "lead": "Every order — standard or pre-order — follows a documented process with confirmed pricing, clear timelines, and WhatsApp tracking from dispatch to delivery."
      },
      "blocks": {
        "step_1": {
          "type": "step",
          "settings": {
            "number": "01",
            "title": "Select Your Products",
            "text": "Choose your hair type, colour, and quantity from our catalogue. Mix colours within the same product line — 1B, 27#, BUG, and 613# all available. Confirm availability before proceeding."
          }
        },
        "step_2": {
          "type": "step",
          "settings": {
            "number": "02",
            "title": "Confirm Pricing & Pay",
            "text": "Receive a confirmed price list based on your order and account tier. Pay via Paystack, Flutterwave, or direct bank transfer. Order is confirmed in writing upon cleared payment — no informal commitments."
          }
        },
        "step_3": {
          "type": "step",
          "settings": {
            "number": "03",
            "title": "Track Your Order",
            "text": "Receive WhatsApp updates at defined milestones — order confirmed, dispatched, and in transit. One communication channel per order. Same-day Lagos dispatch for orders confirmed before 12pm."
          }
        },
        "step_4": {
          "type": "step",
          "settings": {
            "number": "04",
            "title": "Receive Your Delivery",
            "text": "Delivered to all 36 states via GIG Logistics and DHL Nigeria. Lagos 24–48 hours. Abuja and Port Harcourt 1–2 days. Remote states 2–4 days. Delivery confirmation issued on completion."
          }
        }
      },
      "block_order": ["step_1", "step_2", "step_3", "step_4"]
    },
    "cta_banner": {
      "type": "cta-banner",
      "settings": {
        "eyebrow": "Pre-Order Now Open",
        "title": "Order Today.",
        "title_italic": "5% Off Your Entire Order.",
        "text": "Bone Straight Braiding Hair, French Curl, and Deep Wave Bulk — all in stock and available for immediate pre-order at 5% below standard pricing. Wholesale accounts receive additional discounts. No commitment required to enquire.",
        "cta1_text": "Place Pre-Order Now",
        "cta1_url": "/collections/all",
        "cta2_text": "Speak to Us on WhatsApp",
        "cta2_url": "/pages/contact"
      }
    }
  },
  "order": [
    "hero",
    "featured_products",
    "divider_2",
    "about_us",
    "buyer_tiers",
    "how_to_order",
    "cta_banner"
  ]
}
